starrail/__init__.py
starrail/client.py
starrail/utils.py
starrail.py-0.0.2.dist-info/LICENSE
starrail.py-0.0.2.dist-info/METADATA
starrail.py-0.0.2.dist-info/WHEEL
starrail.py-0.0.2.dist-info/top_level.txt
starrail.py-0.0.2.dist-info/RECORD
