Metadata-Version: 2.1
Name: starrail.py
Version: 0.0.2
Summary: This Python module provides the ability to create captivating character cards based on player data from Honkai Star Rail, obtained through their unique user identifiers (UIDs). StarRailCard streamlines the process of generating personalized character assembly cards, relying on the information provided by players.
Home-page: https://github.com/DEViantUA/StarRailCard
Author: DeviantUa
Author-email: deviantapi@gmail.com
Keywords: honkai,cards,generation,honkaistarraill,raill,starraill,builds,honkairail,honkai
Classifier: Programming Language :: Python :: 3
Classifier: License :: OSI Approved :: MIT License
Classifier: Operating System :: OS Independent
Requires-Python: >=3.9
License-File: LICENSE
Requires-Dist: pydantic
Requires-Dist: aiohttp
Requires-Dist: cachetools
Requires-Dist: Pillow
Requires-Dist: aiofiles
Requires-Dist: imageio
Requires-Dist: moviepy
Requires-Dist: more-itertools
Requires-Dist: numpy
Requires-Dist: beautifulsoup4
Requires-Dist: anyio
